Metadata-Version: 2.1
Name: python-lambda2
Version: 3.4.3
Summary: The bare minimum for a Python app running on Amazon Lambda.
Home-page: https://github.com/wassimsalib/python-lambda2
Author: Wassim Salib
Author-email: wassim87@gmail.com
License: ISCL
Keywords: python-lambda2
Platform: UNKNOWN
Classifier: Development Status :: 2 - Pre-Alpha
Classifier: Intended Audience :: Developers
Classifier: License :: OSI Approved :: ISC License (ISCL)
Classifier: Natural Language :: English
Classifier: Programming Language :: Python :: 2
Classifier: Programming Language :: Python :: 2.6
Classifier: Programming Language :: Python :: 2.7
Classifier: Programming Language :: Python :: 3
Classifier: Programming Language :: Python :: 3.3
Classifier: Programming Language :: Python :: 3.4
Classifier: Programming Language :: Python :: 3.5
Classifier: Programming Language :: Python :: 3.6
License-File: LICENSE
Requires-Dist: boto3
Requires-Dist: click
Requires-Dist: PyYAML
